_ATAX/LICENSE
_ATAX/README.rst
_ATAX/VERSION.py
_ATAX/__init__.py
_ATAX/accounting.py
_ATAX/anlagenverzeichnis.py
_ATAX/fahrtenbuch.py
_ATAX/fahrtenbuch_p.py
_ATAX/income_tax_at.py
_ATAX/jahresabschluss.py
_ATAX/kassabuch.py
_ATAX/setup.cfg
_ATAX/setup.py
_ATAX/umsatzsteuer.py
ATAX-3.9.dist-info/LICENSE
ATAX-3.9.dist-info/METADATA
ATAX-3.9.dist-info/WHEEL
ATAX-3.9.dist-info/top_level.txt
ATAX-3.9.dist-info/RECORD
