Metadata-Version: 2.1
Name: ATAX
Version: 3.9
Summary: Package for doing Einnahmen-Ausgabenrechnung according to Austrian tax laws.
Home-page: https://codeberg.org/tanzer/tapyr
Author: Christian Tanzer
Author-email: tanzer@swing.co.at
License: BSD License
Platform: Any
Classifier: Development Status :: 5 - Production/Stable
Classifier: License :: OSI Approved :: BSD License
Classifier: Operating System :: OS Independent
Classifier: Programming Language :: Python
Classifier: Topic :: Office/Business :: Financial :: Accounting
Requires-Python: >=3.9
License-File: LICENSE
Requires-Dist: TFL (>=3)
Requires-Dist: CAL (>=3)
